{"generated_at": "2026-06-24T14:48:56.307407+00:00", "stations": [{"n": "Whitefield (Kadugodi)", "la": 12.9882, "lo": 77.75, "ln": "Purple", "st": "op", "c": "Bengaluru"}, {"n": "Channasandra", "la": 12.9943, "lo": 77.7171, "ln": "Purple", "st": "op", "c": "Bengaluru"}, {"n": "Kadugodi Tree Park", "la": 12.9921, "lo": 77.7042, "ln": "Purple", "st": "op", "c": "Bengaluru"}, {"n": "Hopefarm Channasandra", "la": 12.9885, "lo": 77.6927, "ln": "Purple", "st": "op", "c": "Bengaluru"}, {"n": "Kundalahalli", "la": 12.9842, "lo": 77.6826, "ln": "Purple", "st": "op", "c": "Bengaluru"}, {"n": "Brookefield", "la": 12.9815, "lo": 77.6717, "ln": "Purple", "st": "op", "c": "Bengaluru"}, {"n": "Tin Factory", "la": 12.978, "lo": 77.6646, "ln": "Purple", "st": "op", "c": "Bengaluru"}, {"n": "Krishnarajapura", "la": 13.0022, "lo": 77.6944, "ln": "Purple", "st": "op", "c": "Bengaluru"}, {"n": "Benniganahalli", "la": 12.9916, "lo": 77.6547, "ln": "Purple", "st": "op", "c": "Bengaluru"}, {"n": "Baiyappanahalli", "la": 12.9948, "lo": 77.647, "ln": "Purple", "st": "op", "c": "Bengaluru"}, {"n": "Swami Vivekananda Road", "la": 12.9895, "lo": 77.6403, "ln": "Purple", "st": "op", "c": "Bengaluru"}, {"n": "Indiranagar", "la": 12.9784, "lo": 77.6408, "ln": "Purple", "st": "op", "c": "Bengaluru"}, {"n": "Halasuru", "la": 12.9763, "lo": 77.6259, "ln": "Purple", "st": "op", "c": "Bengaluru"}, {"n": "Trinity", "la": 12.9698, "lo": 77.6204, "ln": "Purple", "st": "op", "c": "Bengaluru"}, {"n": "Mg Road", "la": 12.9756, "lo": 77.6101, "ln": "Purple", "st": "op", "c": "Bengaluru"}, {"n": "Cubbon Park", "la": 12.9789, "lo": 77.5949, "ln": "Purple", "st": "op", "c": "Bengaluru"}, {"n": "Vidhana Soudha", "la": 12.9788, "lo": 77.5905, "ln": "Purple", "st": "op", "c": "Bengaluru"}, {"n": "Sir M Visveshwaraya", "la": 12.9759, "lo": 77.5796, "ln": "Purple", "st": "op", "c": "Bengaluru"}, {"n": "Nadaprabhu Kempegowda (Majestic)", "la": 12.9767, "lo": 77.5713, "ln": "Purple", "st": "op", "c": "Bengaluru"}, {"n": "City Railway Station", "la": 12.9774, "lo": 77.564, "ln": "Purple", "st": "op", "c": "Bengaluru"}, {"n": "Magadi Road", "la": 12.9755, "lo": 77.557, "ln": "Purple", "st": "op", "c": "Bengaluru"}, {"n": "Hosahalli", "la": 12.9701, "lo": 77.5462, "ln": "Purple", "st": "op", "c": "Bengaluru"}, {"n": "Vijayanagar", "la": 12.9669, "lo": 77.5373, "ln": "Purple", "st": "op", "c": "Bengaluru"}, {"n": "Attiguppe", "la": 12.9563, "lo": 77.5341, "ln": "Purple", "st": "op", "c": "Bengaluru"}, {"n": "Deepanjali Nagar", "la": 12.9468, "lo": 77.5312, "ln": "Purple", "st": "op", "c": "Bengaluru"}, {"n": "Mysore Road", "la": 12.9431, "lo": 77.5233, "ln": "Purple", "st": "op", "c": "Bengaluru"}, {"n": "Pantharapalya", "la": 12.9354, "lo": 77.5183, "ln": "Purple", "st": "op", "c": "Bengaluru"}, {"n": "Nayandahalli", "la": 12.9294, "lo": 77.5098, "ln": "Purple", "st": "op", "c": "Bengaluru"}, {"n": "Rajarajeshwari Nagar", "la": 12.918, "lo": 77.5022, "ln": "Purple", "st": "op", "c": "Bengaluru"}, {"n": "Jnanabharathi", "la": 12.9117, "lo": 77.5001, "ln": "Purple", "st": "op", "c": "Bengaluru"}, {"n": "Pattanagere", "la": 12.9049, "lo": 77.496, "ln": "Purple", "st": "op", "c": "Bengaluru"}, {"n": "Kengeri Bus Terminal", "la": 12.9004, "lo": 77.4872, "ln": "Purple", "st": "op", "c": "Bengaluru"}, {"n": "Kengeri", "la": 12.8972, "lo": 77.4827, "ln": "Purple", "st": "op", "c": "Bengaluru"}, {"n": "Challaghatta", "la": 12.8927, "lo": 77.4769, "ln": "Purple", "st": "op", "c": "Bengaluru"}, {"n": "Madavara", "la": 13.0938, "lo": 77.5003, "ln": "Green", "st": "op", "c": "Bengaluru"}, {"n": "Chikkabidarakallu", "la": 13.0793, "lo": 77.5052, "ln": "Green", "st": "op", "c": "Bengaluru"}, {"n": "Manjunathanagar", "la": 13.0653, "lo": 77.511, "ln": "Green", "st": "op", "c": "Bengaluru"}, {"n": "Nagasandra", "la": 13.0496, "lo": 77.5173, "ln": "Green", "st": "op", "c": "Bengaluru"}, {"n": "Dasarahalli", "la": 13.0393, "lo": 77.5226, "ln": "Green", "st": "op", "c": "Bengaluru"}, {"n": "Jalahalli", "la": 13.029, "lo": 77.5289, "ln": "Green", "st": "op", "c": "Bengaluru"}, {"n": "Peenya Industry", "la": 13.0227, "lo": 77.537, "ln": "Green", "st": "op", "c": "Bengaluru"}, {"n": "Peenya", "la": 13.0165, "lo": 77.5432, "ln": "Green", "st": "op", "c": "Bengaluru"}, {"n": "Goraguntepalya", "la": 13.0094, "lo": 77.5495, "ln": "Green", "st": "op", "c": "Bengaluru"}, {"n": "Yeshwanthpur", "la": 13.0271, "lo": 77.5551, "ln": "Green", "st": "op", "c": "Bengaluru"}, {"n": "Sandal Soap Factory", "la": 13.0211, "lo": 77.5618, "ln": "Green", "st": "op", "c": "Bengaluru"}, {"n": "Mahalakshmi", "la": 13.0133, "lo": 77.5679, "ln": "Green", "st": "op", "c": "Bengaluru"}, {"n": "Rajajinagar", "la": 13.0042, "lo": 77.5665, "ln": "Green", "st": "op", "c": "Bengaluru"}, {"n": "Mahakavi Kuvempu Road", "la": 12.9979, "lo": 77.5696, "ln": "Green", "st": "op", "c": "Bengaluru"}, {"n": "Srirampura", "la": 12.9904, "lo": 77.5706, "ln": "Green", "st": "op", "c": "Bengaluru"}, {"n": "Mantri Square Sampige Road", "la": 12.9862, "lo": 77.5733, "ln": "Green", "st": "op", "c": "Bengaluru"}, {"n": "Chickpete", "la": 12.9659, "lo": 77.5762, "ln": "Green", "st": "op", "c": "Bengaluru"}, {"n": "Krishna Rajendra Market", "la": 12.9606, "lo": 77.5779, "ln": "Green", "st": "op", "c": "Bengaluru"}, {"n": "National College", "la": 12.9537, "lo": 77.5779, "ln": "Green", "st": "op", "c": "Bengaluru"}, {"n": "Lalbagh", "la": 12.9509, "lo": 77.5816, "ln": "Green", "st": "op", "c": "Bengaluru"}, {"n": "South End Circle", "la": 12.9454, "lo": 77.5854, "ln": "Green", "st": "op", "c": "Bengaluru"}, {"n": "Jayanagar", "la": 12.9304, "lo": 77.5845, "ln": "Green", "st": "op", "c": "Bengaluru"}, {"n": "Rashtreeya Vidyalaya Road", "la": 12.9226, "lo": 77.5922, "ln": "Green", "st": "op", "c": "Bengaluru"}, {"n": "Banashankari", "la": 12.9137, "lo": 77.5792, "ln": "Green", "st": "op", "c": "Bengaluru"}, {"n": "Jaya Prakash Nagar", "la": 12.9097, "lo": 77.5846, "ln": "Green", "st": "op", "c": "Bengaluru"}, {"n": "Puttenahalli", "la": 12.9032, "lo": 77.5895, "ln": "Green", "st": "op", "c": "Bengaluru"}, {"n": "Yelachenahalli", "la": 12.8961, "lo": 77.5948, "ln": "Green", "st": "op", "c": "Bengaluru"}, {"n": "Konanakunte Cross", "la": 12.8862, "lo": 77.5962, "ln": "Green", "st": "op", "c": "Bengaluru"}, {"n": "Doddakallasandra", "la": 12.8787, "lo": 77.5976, "ln": "Green", "st": "op", "c": "Bengaluru"}, {"n": "Vajarahalli", "la": 12.8694, "lo": 77.5989, "ln": "Green", "st": "op", "c": "Bengaluru"}, {"n": "Talaghattapura", "la": 12.8582, "lo": 77.5943, "ln": "Green", "st": "op", "c": "Bengaluru"}, {"n": "Silk Institute", "la": 12.8469, "lo": 77.5812, "ln": "Green", "st": "op", "c": "Bengaluru"}, {"n": "Rashtreeya Vidyalaya Road", "la": 12.9226, "lo": 77.5922, "ln": "Yellow", "st": "op", "c": "Bengaluru"}, {"n": "Ragigudda", "la": 12.909, "lo": 77.601, "ln": "Yellow", "st": "op", "c": "Bengaluru"}, {"n": "Jayadeva Hospital", "la": 12.9006, "lo": 77.6105, "ln": "Yellow", "st": "op", "c": "Bengaluru"}, {"n": "Btm Layout", "la": 12.8942, "lo": 77.6148, "ln": "Yellow", "st": "op", "c": "Bengaluru"}, {"n": "Central Silk Board", "la": 12.9172, "lo": 77.622, "ln": "Yellow", "st": "op", "c": "Bengaluru"}, {"n": "Hongasandra", "la": 12.884, "lo": 77.6298, "ln": "Yellow", "st": "op", "c": "Bengaluru"}, {"n": "Kudlu Gate", "la": 12.8752, "lo": 77.639, "ln": "Yellow", "st": "op", "c": "Bengaluru"}, {"n": "Singasandra", "la": 12.8661, "lo": 77.6482, "ln": "Yellow", "st": "op", "c": "Bengaluru"}, {"n": "Hosa Road", "la": 12.8558, "lo": 77.658, "ln": "Yellow", "st": "op", "c": "Bengaluru"}, {"n": "Electronic City", "la": 12.8399, "lo": 77.6745, "ln": "Yellow", "st": "op", "c": "Bengaluru"}, {"n": "Infosys Foundation Konappana Agrahara", "la": 12.8326, "lo": 77.6815, "ln": "Yellow", "st": "op", "c": "Bengaluru"}, {"n": "Beratena Agrahara", "la": 12.8264, "lo": 77.6891, "ln": "Yellow", "st": "op", "c": "Bengaluru"}, {"n": "Hebbagodi", "la": 12.817, "lo": 77.692, "ln": "Yellow", "st": "op", "c": "Bengaluru"}, {"n": "Huskur Road", "la": 12.8081, "lo": 77.6941, "ln": "Yellow", "st": "op", "c": "Bengaluru"}, {"n": "Bommasandra", "la": 12.7951, "lo": 77.6932, "ln": "Yellow", "st": "op", "c": "Bengaluru"}, {"n": "Delta Electronics Bommasandra", "la": 12.7832, "lo": 77.6912, "ln": "Yellow", "st": "op", "c": "Bengaluru"}, {"n": "Silk Board (Blue Line)", "la": 12.9172, "lo": 77.622, "ln": "Blue Phase 2A", "st": "uc", "c": "Bengaluru"}, {"n": "Kr Puram", "la": 13.0022, "lo": 77.6944, "ln": "Blue Phase 2A", "st": "uc", "c": "Bengaluru"}, {"n": "Kempegowda International Airport", "la": 13.1989, "lo": 77.7068, "ln": "Blue Phase 2B", "st": "uc", "c": "Bengaluru"}, {"n": "Rajiv Chowk", "la": 28.6328, "lo": 77.2197, "ln": "Yellow", "st": "op", "c": "Delhi"}, {"n": "Aiims", "la": 28.5689, "lo": 77.2077, "ln": "Yellow", "st": "op", "c": "Delhi"}, {"n": "Hauz Khas", "la": 28.5432, "lo": 77.2066, "ln": "Yellow", "st": "op", "c": "Delhi"}, {"n": "New Delhi Railway Station", "la": 28.6435, "lo": 77.2193, "ln": "Yellow", "st": "op", "c": "Delhi"}, {"n": "Kashmere Gate", "la": 28.6677, "lo": 77.2285, "ln": "Yellow", "st": "op", "c": "Delhi"}, {"n": "Dwarka Sector 21", "la": 28.5526, "lo": 77.0593, "ln": "Blue", "st": "op", "c": "Delhi"}, {"n": "Noida City Centre", "la": 28.5706, "lo": 77.3588, "ln": "Blue", "st": "op", "c": "Delhi"}, {"n": "Botanical Garden", "la": 28.5637, "lo": 77.337, "ln": "Blue", "st": "op", "c": "Delhi"}, {"n": "Igi Airport T3", "la": 28.5565, "lo": 77.0882, "ln": "Orange (Airport Express)", "st": "op", "c": "Delhi"}, {"n": "Janakpuri West", "la": 28.6262, "lo": 77.0855, "ln": "Blue", "st": "op", "c": "Delhi"}, {"n": "Lajpat Nagar", "la": 28.5677, "lo": 77.2394, "ln": "Pink", "st": "op", "c": "Delhi"}, {"n": "Mayur Vihar Phase 1", "la": 28.6082, "lo": 77.2968, "ln": "Blue", "st": "op", "c": "Delhi"}, {"n": "Anand Vihar", "la": 28.6468, "lo": 77.3158, "ln": "Blue", "st": "op", "c": "Delhi"}, {"n": "Samaypur Badli", "la": 28.7327, "lo": 77.1554, "ln": "Yellow", "st": "op", "c": "Delhi"}, {"n": "Noida Sector 137", "la": 28.5406, "lo": 77.3869, "ln": "Aqua", "st": "op", "c": "Noida"}, {"n": "Pari Chowk", "la": 28.4721, "lo": 77.5062, "ln": "Aqua", "st": "op", "c": "Noida"}, {"n": "Sikanderpur", "la": 28.4794, "lo": 77.0906, "ln": "Rapid Metro", "st": "op", "c": "Gurugram"}, {"n": "Cyber City", "la": 28.495, "lo": 77.0891, "ln": "Rapid Metro", "st": "op", "c": "Gurugram"}, {"n": "Miyapur", "la": 17.4963, "lo": 78.3485, "ln": "Red", "st": "op", "c": "Hyderabad"}, {"n": "Hitech City", "la": 17.4478, "lo": 78.3768, "ln": "Red", "st": "op", "c": "Hyderabad"}, {"n": "Ameerpet", "la": 17.4376, "lo": 78.449, "ln": "Red/Blue", "st": "op", "c": "Hyderabad"}, {"n": "Lb Nagar", "la": 17.3468, "lo": 78.5499, "ln": "Red", "st": "op", "c": "Hyderabad"}, {"n": "Nagole", "la": 17.3699, "lo": 78.5528, "ln": "Blue", "st": "op", "c": "Hyderabad"}, {"n": "Raidurg", "la": 17.4228, "lo": 78.38, "ln": "Blue", "st": "op", "c": "Hyderabad"}, {"n": "Jbs Parade Ground", "la": 17.4402, "lo": 78.498, "ln": "Green", "st": "op", "c": "Hyderabad"}, {"n": "Mg Bus Station", "la": 17.3764, "lo": 78.4803, "ln": "Red/Green", "st": "op", "c": "Hyderabad"}, {"n": "Dilsukhnagar", "la": 17.3673, "lo": 78.5266, "ln": "Red", "st": "op", "c": "Hyderabad"}, {"n": "Uppal", "la": 17.3967, "lo": 78.5596, "ln": "Blue", "st": "op", "c": "Hyderabad"}, {"n": "Begumpet", "la": 17.4456, "lo": 78.4694, "ln": "Blue", "st": "op", "c": "Hyderabad"}, {"n": "Secunderabad West", "la": 17.4343, "lo": 78.4876, "ln": "Blue", "st": "op", "c": "Hyderabad"}, {"n": "Wimco Nagar", "la": 13.1437, "lo": 80.2949, "ln": "Line 1", "st": "op", "c": "Chennai"}, {"n": "Chennai Central", "la": 13.0828, "lo": 80.275, "ln": "Line 1", "st": "op", "c": "Chennai"}, {"n": "Koyambedu", "la": 13.0694, "lo": 80.1956, "ln": "Line 1", "st": "op", "c": "Chennai"}, {"n": "Chennai Airport", "la": 12.9941, "lo": 80.1708, "ln": "Line 1", "st": "op", "c": "Chennai"}, {"n": "Alandur", "la": 12.9984, "lo": 80.2064, "ln": "Line 1", "st": "op", "c": "Chennai"}, {"n": "Velachery", "la": 12.9804, "lo": 80.2209, "ln": "Line 2", "st": "op", "c": "Chennai"}, {"n": "St Thomas Mount", "la": 13.0043, "lo": 80.2025, "ln": "Line 2", "st": "op", "c": "Chennai"}, {"n": "Anna Nagar Tower", "la": 13.0851, "lo": 80.2098, "ln": "Line 2", "st": "op", "c": "Chennai"}, {"n": "Sholinganallur", "la": 12.9004, "lo": 80.227, "ln": "Line 2", "st": "op", "c": "Chennai"}, {"n": "Versova", "la": 19.1313, "lo": 72.8164, "ln": "Line 1", "st": "op", "c": "Mumbai"}, {"n": "Andheri", "la": 19.1197, "lo": 72.8487, "ln": "Line 1", "st": "op", "c": "Mumbai"}, {"n": "Ghatkopar", "la": 19.0864, "lo": 72.9074, "ln": "Line 1", "st": "op", "c": "Mumbai"}, {"n": "Dahisar West", "la": 19.2518, "lo": 72.8527, "ln": "Line 2A", "st": "op", "c": "Mumbai"}, {"n": "Borivali West", "la": 19.231, "lo": 72.8529, "ln": "Line 2A", "st": "op", "c": "Mumbai"}, {"n": "Goregaon West", "la": 19.1602, "lo": 72.843, "ln": "Line 2A", "st": "op", "c": "Mumbai"}, {"n": "Dahisar East", "la": 19.242, "lo": 72.867, "ln": "Line 7", "st": "op", "c": "Mumbai"}, {"n": "Goregaon East", "la": 19.1567, "lo": 72.8701, "ln": "Line 7", "st": "op", "c": "Mumbai"}, {"n": "Bkc", "la": 19.0645, "lo": 72.8693, "ln": "Line 2B", "st": "uc", "c": "Mumbai"}, {"n": "Dakshineswar", "la": 22.6447, "lo": 88.3584, "ln": "Blue Line", "st": "op", "c": "Kolkata"}, {"n": "Dum Dum", "la": 22.623, "lo": 88.4023, "ln": "Blue Line", "st": "op", "c": "Kolkata"}, {"n": "Esplanade", "la": 22.57, "lo": 88.3525, "ln": "Blue/Green", "st": "op", "c": "Kolkata"}, {"n": "Park Street", "la": 22.553, "lo": 88.3519, "ln": "Blue Line", "st": "op", "c": "Kolkata"}, {"n": "Tollygunge", "la": 22.5099, "lo": 88.3502, "ln": "Blue Line", "st": "op", "c": "Kolkata"}, {"n": "Howrah Maidan", "la": 22.5847, "lo": 88.335, "ln": "Green Line", "st": "op", "c": "Kolkata"}, {"n": "Salt Lake Sector V", "la": 22.575, "lo": 88.4305, "ln": "Green Line", "st": "op", "c": "Kolkata"}, {"n": "Pcmc Bhavan", "la": 18.6315, "lo": 73.8058, "ln": "Line 1", "st": "op", "c": "Pune"}, {"n": "Shivajinagar", "la": 18.5292, "lo": 73.8396, "ln": "Line 1", "st": "op", "c": "Pune"}, {"n": "Pune Railway Station", "la": 18.529, "lo": 73.8739, "ln": "Line 1", "st": "op", "c": "Pune"}, {"n": "Ramwadi", "la": 18.5542, "lo": 73.9196, "ln": "Line 1", "st": "op", "c": "Pune"}, {"n": "Vanaz", "la": 18.5064, "lo": 73.8171, "ln": "Line 2", "st": "op", "c": "Pune"}, {"n": "Civil Court", "la": 18.514, "lo": 73.8576, "ln": "Line 1", "st": "op", "c": "Pune"}, {"n": "Motera Stadium", "la": 23.0996, "lo": 72.5988, "ln": "Line 1", "st": "op", "c": "Ahmedabad"}, {"n": "Kalupur Railway Station", "la": 23.0339, "lo": 72.5987, "ln": "Line 1", "st": "op", "c": "Ahmedabad"}, {"n": "Old High Court", "la": 23.0334, "lo": 72.5793, "ln": "Line 1", "st": "op", "c": "Ahmedabad"}, {"n": "Vastral Gam", "la": 23.01, "lo": 72.6702, "ln": "Line 1", "st": "op", "c": "Ahmedabad"}, {"n": "Thaltej Gam", "la": 23.0677, "lo": 72.5062, "ln": "Line 2", "st": "op", "c": "Ahmedabad"}, {"n": "Gandhinagar Capital", "la": 23.2156, "lo": 72.6369, "ln": "Line 1", "st": "op", "c": "Ahmedabad"}, {"n": "Aluva", "la": 10.1078, "lo": 76.3515, "ln": "Line 1", "st": "op", "c": "Kochi"}, {"n": "Edapally", "la": 10.0214, "lo": 76.3042, "ln": "Line 1", "st": "op", "c": "Kochi"}, {"n": "Mg Road", "la": 9.9312, "lo": 76.2673, "ln": "Line 1", "st": "op", "c": "Kochi"}, {"n": "Vyttila", "la": 9.953, "lo": 76.3082, "ln": "Line 1", "st": "op", "c": "Kochi"}, {"n": "Tripunithura", "la": 9.9448, "lo": 76.3458, "ln": "Line 1", "st": "op", "c": "Kochi"}, {"n": "Chandpole", "la": 26.9233, "lo": 75.806, "ln": "Line 1", "st": "op", "c": "Jaipur"}, {"n": "Mansarovar", "la": 26.8607, "lo": 75.7535, "ln": "Line 1", "st": "op", "c": "Jaipur"}, {"n": "Civil Lines", "la": 26.9174, "lo": 75.789, "ln": "Line 1", "st": "op", "c": "Jaipur"}, {"n": "Ccs Airport", "la": 26.7636, "lo": 80.8955, "ln": "NS Corridor", "st": "op", "c": "Lucknow"}, {"n": "Hazratganj", "la": 26.8472, "lo": 80.9462, "ln": "NS Corridor", "st": "op", "c": "Lucknow"}, {"n": "Alambagh Bus Station", "la": 26.8153, "lo": 80.9105, "ln": "NS Corridor", "st": "op", "c": "Lucknow"}, {"n": "Sitabuldi Interchange", "la": 21.149, "lo": 79.0731, "ln": "Line 1/2", "st": "op", "c": "Nagpur"}, {"n": "Kasturchand Park", "la": 21.1547, "lo": 79.0784, "ln": "Line 1", "st": "op", "c": "Nagpur"}, {"n": "Prajapati Nagar", "la": 21.0668, "lo": 79.0714, "ln": "Line 1", "st": "op", "c": "Nagpur"}, {"n": "Aiims Bhopal", "la": 23.193, "lo": 77.414, "ln": "Line 1", "st": "uc", "c": "Bhopal"}, {"n": "Rajwada", "la": 22.7196, "lo": 75.8577, "ln": "Line 1", "st": "uc", "c": "Indore"}, {"n": "Patna Junction", "la": 25.5941, "lo": 85.1376, "ln": "Line 1", "st": "uc", "c": "Patna"}, {"n": "Bhubaneswar Railway Station", "la": 20.2706, "lo": 85.8365, "ln": "Line 1", "st": "uc", "c": "Bhubaneswar"}, {"n": "Steel Plant", "la": 17.693, "lo": 83.2185, "ln": "Line 1", "st": "uc", "c": "Visakhapatnam"}, {"n": "Surat Railway Station", "la": 21.2062, "lo": 72.9722, "ln": "Line 1", "st": "uc", "c": "Surat"}, {"n": "Meerut Central (Rrts)", "la": 28.9845, "lo": 77.7064, "ln": "RRTS Delhi-Meerut", "st": "uc", "c": "Meerut"}]}